{
  "image_wh": [
    4168,
    2686
  ],
  "rect_LTRB": [
    [
      1184,
      306,
      1712,
      468
    ],
    [
      1606,
      478,
      2008,
      594
    ],
    [
      1144,
      660,
      2178,
      820
    ],
    [
      1826,
      1336,
      2262,
      1458
    ],
    [
      278,
      292,
      3088,
      1834
    ],
    [
      3320,
      286,
      3948,
      2398
    ]
  ],
  "rect_captions": [
    "",
    "",
    "",
    "",
    "",
    ""
  ],
  "rect_classes": [
    7,
    7,
    7,
    7,
    4,
    2
  ],
  "class_names": [
    "No Class",
    "Ignore",
    "Img:CalibrationCard",
    "Img:Seal",
    "Img:WritableArea",
    "Wr:OldText",
    "Wr:OldNote",
    "Wr:NewText",
    "Wr:NewOther",
    "WrO:Ornament",
    "WrO:Fold"
  ],
  "class_colors": [
    "#646B63",
    "#23282B",
    "#763C28",
    "#316650",
    "#00BB2D",
    "#287233",
    "#231A24",
    "#F5D033",
    "#063971",
    "#1E2460",
    "#641C34"
  ],
  "user": "",
  "img_md5": "626cdfababfe1437a87ff81bb98e050a"
}