{"image_wh": [1302, 2282], "rect_LTRB": [[76, 72, 1224, 424], [696, 1390, 1192, 1650], [866, 1762, 998, 1880], [54, 458, 1240, 2222]], "rect_captions": ["", "", "", ""], "rect_classes": [2, 7, 7, 4], "class_names": ["No Class", "Ignore", "Img:CalibrationCard", "Img:Seal", "Img:WritableArea", "Wr:OldText", "Wr:OldNote", "Wr:NewText", "Wr:NewOther", "WrO:Ornament", "WrO:Fold"], "class_colors": ["#646B63", "#23282B", "#763C28", "#316650", "#00BB2D", "#287233", "#231A24", "#F5D033", "#063971", "#1E2460", "#641C34"], "user": ""}