{
  "image_wh": [
    4156,
    3260
  ],
  "rect_LTRB": [
    [
      392,
      454,
      684,
      1182
    ],
    [
      3008,
      2186,
      3096,
      2282
    ],
    [
      516,
      538,
      2964,
      1774
    ],
    [
      1248,
      2474,
      1936,
      3034
    ],
    [
      232,
      326,
      3144,
      2318
    ],
    [
      3268,
      394,
      4028,
      2706
    ]
  ],
  "rect_captions": [
    "",
    "",
    "",
    "",
    "",
    ""
  ],
  "rect_classes": [
    9,
    6,
    5,
    3,
    4,
    2
  ],
  "class_names": [
    "No Class",
    "Ignore",
    "Img:CalibrationCard",
    "Img:Seal",
    "Img:WritableArea",
    "Wr:OldText",
    "Wr:OldNote",
    "Wr:NewText",
    "Wr:NewOther",
    "WrO:Ornament",
    "WrO:Fold"
  ],
  "class_colors": [
    "#646B63",
    "#23282B",
    "#763C28",
    "#316650",
    "#00BB2D",
    "#287233",
    "#231A24",
    "#F5D033",
    "#063971",
    "#1E2460",
    "#641C34"
  ],
  "user": "",
  "img_md5": "a8637a8581d2416185c75eaa3d1f116b"
}