{"image_wh": [7514, 4154], "rect_LTRB": [[6310, 198, 7282, 3430], [300, 262, 1516, 2182], [1254, 370, 5624, 838], [1382, 734, 5586, 2630], [2290, 2418, 3896, 3724], [1324, 2962, 2520, 3486], [216, 158, 352, 280], [5862, 242, 5996, 370], [5836, 3774, 6008, 3942], [236, 3794, 408, 3954], [262, 172, 6008, 3954]], "rect_captions": ["", "", "", "", "", "", "", "", "", "", ""], "rect_classes": [2, 9, 9, 5, 3, 6, 1, 1, 1, 1, 4], "class_names": ["No Class", "Ignore", "Img:CalibrationCard", "Img:Seal", "Img:WritableArea", "Wr:OldText", "Wr:OldNote", "Wr:NewText", "Wr:NewOther", "WrO:Ornament", "WrO:Fold"], "class_colors": ["#646B63", "#23282B", "#763C28", "#316650", "#00BB2D", "#287233", "#231A24", "#F5D033", "#063971", "#1E2460", "#641C34"], "user": ""}