{"image_wh": [3000, 2110], "rect_LTRB": [[502, 212, 828, 300], [1100, 806, 1728, 956], [1072, 1028, 1734, 1152], [1240, 928, 1448, 1082], [1272, 1142, 1506, 1338], [1126, 1578, 1378, 1808], [1496, 1604, 1704, 1808], [406, 182, 2328, 1408], [2390, 36, 2812, 1500]], "rect_captions": ["", "", "", "", "", "", "", "", ""], "rect_classes": [7, 7, 7, 7, 7, 3, 3, 4, 2], "class_names": ["No Class", "Ignore", "Img:CalibrationCard", "Img:Seal", "Img:WritableArea", "Wr:OldText", "Wr:OldNote", "Wr:NewText", "Wr:NewOther", "WrO:Ornament", "WrO:Fold"], "class_colors": ["#646B63", "#23282B", "#763C28", "#316650", "#00BB2D", "#287233", "#231A24", "#F5D033", "#063971", "#1E2460", "#641C34"], "user": ""}