{
  "image_wh": [
    4934,
    4504
  ],
  "rect_LTRB": [
    [
      482,
      404,
      566,
      504
    ],
    [
      3366,
      372,
      3474,
      488
    ],
    [
      354,
      3332,
      450,
      3442
    ],
    [
      3292,
      3304,
      3388,
      3428
    ],
    [
      4192,
      2916,
      4694,
      4138
    ],
    [
      1510,
      1864,
      2316,
      2120
    ],
    [
      1708,
      2152,
      2156,
      2340
    ],
    [
      1836,
      2320,
      2204,
      2494
    ],
    [
      1264,
      2682,
      1976,
      3080
    ],
    [
      1590,
      3740,
      2188,
      4354
    ],
    [
      242,
      316,
      3544,
      3504
    ],
    [
      3788,
      310,
      4704,
      2736
    ]
  ],
  "rect_captions": [
    "",
    "",
    "",
    "",
    "",
    "",
    "",
    "",
    "",
    "",
    "",
    ""
  ],
  "rect_classes": [
    1,
    1,
    1,
    1,
    1,
    7,
    7,
    7,
    7,
    3,
    4,
    2
  ],
  "class_names": [
    "No Class",
    "Ignore",
    "Img:CalibrationCard",
    "Img:Seal",
    "Img:WritableArea",
    "Wr:OldText",
    "Wr:OldNote",
    "Wr:NewText",
    "Wr:NewOther",
    "WrO:Ornament",
    "WrO:Fold"
  ],
  "class_colors": [
    "#646B63",
    "#23282B",
    "#763C28",
    "#316650",
    "#00BB2D",
    "#287233",
    "#231A24",
    "#F5D033",
    "#063971",
    "#1E2460",
    "#641C34"
  ],
  "user": "",
  "img_md5": "8c1f3163b04219a6c3674d5a23523adf"
}