{"image_wh": [3000, 2092], "rect_LTRB": [[1456, 616, 1554, 706], [1462, 1030, 1556, 1138], [1454, 1240, 1544, 1352], [1576, 560, 2112, 738], [1822, 1000, 2254, 1192], [370, 256, 1330, 1616], [1554, 266, 2456, 572], [1556, 732, 2242, 1026], [1576, 1170, 2290, 1472], [180, 104, 2478, 1964], [2574, 308, 2910, 1478]], "rect_captions": ["", "", "", "", "", "", "", "", "", "", ""], "rect_classes": [3, 3, 3, 6, 6, 5, 5, 5, 5, 4, 2], "class_names": ["No Class", "Ignore", "Img:CalibrationCard", "Img:Seal", "Img:WritableArea", "Wr:OldText", "Wr:OldNote", "Wr:NewText", "Wr:NewOther", "WrO:Ornament", "WrO:Fold"], "class_colors": ["#646B63", "#23282B", "#763C28", "#316650", "#00BB2D", "#287233", "#231A24", "#F5D033", "#063971", "#1E2460", "#641C34"], "user": ""}