{
  "image_wh": [
    2742,
    3830
  ],
  "rect_LTRB": [
    [
      654,
      28,
      2730,
      322
    ],
    [
      12,
      340,
      600,
      2278
    ],
    [
      6,
      3496,
      2736,
      3820
    ],
    [
      1392,
      382,
      2652,
      526
    ],
    [
      852,
      418,
      1200,
      538
    ],
    [
      846,
      3124,
      1470,
      3424
    ],
    [
      1602,
      3148,
      1836,
      3388
    ],
    [
      660,
      508,
      1020,
      1486
    ],
    [
      978,
      556,
      2694,
      838
    ],
    [
      978,
      790,
      2700,
      3178
    ],
    [
      666,
      382,
      2718,
      3466
    ]
  ],
  "rect_captions": [
    "",
    "",
    "",
    "",
    "",
    "",
    "",
    "",
    "",
    "",
    ""
  ],
  "rect_classes": [
    2,
    2,
    1,
    7,
    7,
    7,
    8,
    9,
    9,
    5,
    4
  ],
  "class_names": [
    "No Class",
    "Ignore",
    "Img:CalibrationCard",
    "Img:Seal",
    "Img:WritableArea",
    "Wr:OldText",
    "Wr:OldNote",
    "Wr:NewText",
    "Wr:NewOther",
    "WrO:Ornament",
    "WrO:Fold"
  ],
  "class_colors": [
    "#646B63",
    "#23282B",
    "#763C28",
    "#316650",
    "#00BB2D",
    "#287233",
    "#231A24",
    "#F5D033",
    "#063971",
    "#1E2460",
    "#641C34"
  ],
  "user": "",
  "img_md5": "e84b5ac4ffd94e9e5d8a8bc98cd16e26"
}