{"image_wh": [5526, 3560], "rect_LTRB": [[376, 292, 448, 368], [2278, 336, 2336, 406], [4082, 304, 4168, 386], [2032, 2716, 2524, 3318], [290, 2060, 4184, 2588], [892, 250, 1996, 678], [962, 602, 3888, 1334], [866, 1294, 1314, 1536], [962, 1440, 3896, 1984], [310, 224, 4180, 2594], [4558, 228, 5274, 2186], [4832, 2316, 5236, 3314]], "rect_captions": ["", "", "", "", "", "", "", "", "", "", "", ""], "rect_classes": [1, 1, 1, 3, 10, 9, 5, 9, 5, 4, 2, 1], "class_names": ["No Class", "Ignore", "Img:CalibrationCard", "Img:Seal", "Img:WritableArea", "Wr:OldText", "Wr:OldNote", "Wr:NewText", "Wr:NewOther", "WrO:Ornament", "WrO:Fold"], "class_colors": ["#646B63", "#23282B", "#763C28", "#316650", "#00BB2D", "#287233", "#231A24", "#F5D033", "#063971", "#1E2460", "#641C34"], "user": ""}