{"image_wh": [1418, 2288], "rect_LTRB": [[144, 52, 1302, 408], [774, 1396, 1282, 1684], [940, 1722, 1080, 1796], [98, 446, 1302, 2210]], "rect_captions": ["", "", "", ""], "rect_classes": [2, 7, 7, 4], "class_names": ["No Class", "Ignore", "Img:CalibrationCard", "Img:Seal", "Img:WritableArea", "Wr:OldText", "Wr:OldNote", "Wr:NewText", "Wr:NewOther", "WrO:Ornament", "WrO:Fold"], "class_colors": ["#646B63", "#23282B", "#763C28", "#316650", "#00BB2D", "#287233", "#231A24", "#F5D033", "#063971", "#1E2460", "#641C34"], "user": ""}